[/* 1 */
  {
    "_id" : "5257fe5eb9b45b4529000004",
    "wallet" : {
      "currency" : "GBP"
    }
  },

  /* 2 */
  {
    "_id" : "52776ffb37595e8e4d000003",
    "wallet" : {
      "currency" : "EUR"
    }
  },

  /* 3 */
  {
    "_id" : "527774fd49b185594e000003",
    "wallet" : {
      "currency" : "EUR"
    }
  },

  /* 4 */
  {
    "_id" : "52793b8a323f8e4e77000004",
    "wallet" : {
      "currency" : "EUR"
    }
  },

  /* 5 */
  {
    "_id" : "527a1ed4323f8e4e77000008",
    "wallet" : {
      "currency" : "USD"
    }
  },

  /* 6 */
  {
    "_id" : "527a43176867df6058000014",
    "wallet" : {
      "currency" : "EUR"
    }
  },

  /* 7 */
  {
    "_id" : "527a43d0323f8e4e7700000c",
    "wallet" : {
      "currency" : "EUR"
    }
  },

  /* 8 */
  {
    "_id" : "527a5123edcdf74f5c000003",
    "wallet" : {
      "currency" : "EUR"
    }
  },

  /* 9 */
  {
    "_id" : "527a513b6b3692477b000003",
    "wallet" : {
      "currency" : "EUR"
    }
  },

  /* 10 */
  {
    "_id" : "527ba4d97a2b14146a000003",
    "wallet" : {
      "currency" : "EUR"
    }
  },

  /* 11 */
  {
    "_id" : "527caa0e712142a60c00000f",
    "wallet" : {
      "currency" : "EUR"
    }
  },

  /* 12 */
  {
    "_id" : "527e044d712142a60c000031",
    "wallet" : {
      "currency" : "EUR"
    }
  },

  /* 13 */
  {
    "_id" : "5280b3e75c92e0046c000045",
    "wallet" : {
      "currency" : "EUR"
    }
  },

  /* 14 */
  {
    "_id" : "5280c5b5712142a60c00003c",
    "wallet" : {
      "currency" : "EUR"
    }
  },

  /* 15 */
  {
    "_id" : "5285615318708dd61e00000c",
    "wallet" : {
      "currency" : "EUR"
    }
  },

  /* 16 */
  {
    "_id" : "528628b95f5d33140e000004",
    "wallet" : {
      "currency" : "EUR"
    }
  },

  /* 17 */
  {
    "_id" : "528b345d4689ee6c2e000011",
    "wallet" : {
      "currency" : "EUR"
    }
  },

  /* 18 */
  {
    "_id" : "528c800f2d8c98753800000a",
    "wallet" : {
      "currency" : "EUR"
    }
  },

  /* 19 */
  {
    "_id" : "528c87adb7ebcbc81b000012",
    "wallet" : {
      "currency" : "EUR"
    }
  },

  /* 20 */
  {
    "_id" : "528c955eb7ebcbc81b000015",
    "wallet" : {
      "currency" : "EUR"
    }
  },

  /* 21 */
  {
    "_id" : "528c95be2d8c98753800000c",
    "wallet" : {
      "currency" : "EUR"
    }
  },

  /* 22 */
  {
    "_id" : "528c981cb7ebcbc81b000017",
    "wallet" : {
      "currency" : "EUR"
    }
  },

  /* 23 */
  {
    "_id" : "528f474d7e1833763f000003",
    "wallet" : {
      "currency" : "EUR"
    }
  },

  /* 24 */
  {
    "_id" : "5291bc09c118d61423000011",
    "wallet" : {
      "currency" : "EUR"
    }
  },

  /* 25 */
  {
    "_id" : "5291fde3c118d61423000015",
    "wallet" : {
      "currency" : "EUR"
    }
  },

  /* 26 */
  {
    "_id" : "5292367fc118d61423000017",
    "wallet" : {
      "currency" : "EUR"
    }
  },

  /* 27 */
  {
    "_id" : "529264753686daaf3f00000d",
    "wallet" : {
      "currency" : "EUR"
    }
  },

  /* 28 */
  {
    "_id" : "52931efdc118d61423000022",
    "wallet" : {
      "currency" : "EUR"
    }
  },

  /* 29 */
  {
    "_id" : "529322783686daaf3f000019",
    "wallet" : {
      "currency" : "EUR"
    }
  },

  /* 30 */
  {
    "_id" : "52932da83686daaf3f00001b",
    "wallet" : {
      "currency" : "EUR"
    }
  },

  /* 31 */
  {
    "_id" : "5293324b3686daaf3f00001d",
    "wallet" : {
      "currency" : "EUR"
    }
  },

  /* 32 */
  {
    "_id" : "5293393c3686daaf3f00001f",
    "wallet" : {
      "currency" : "EUR"
    }
  },

  /* 33 */
  {
    "_id" : "529344b93686daaf3f000028",
    "wallet" : {
      "currency" : "EUR"
    }
  },

  /* 34 */
  {
    "_id" : "5293df7fc118d6142300005d",
    "wallet" : {
      "currency" : "EUR"
    }
  },

  /* 35 */
  {
    "_id" : "52949557c118d61423000066",
    "wallet" : {
      "currency" : "EUR"
    }
  },

  /* 36 */
  {
    "_id" : "52949aaf3686daaf3f000054",
    "wallet" : {
      "currency" : "EUR"
    }
  },

  /* 37 */
  {
    "_id" : "52949e89c118d61423000069",
    "wallet" : {
      "currency" : "EUR"
    }
  },

  /* 38 */
  {
    "_id" : "5295ac53c118d6142300007f",
    "wallet" : {
      "currency" : "EUR"
    }
  },

  /* 39 */
  {
    "_id" : "5295b5d9c118d61423000083",
    "wallet" : {
      "currency" : "EUR"
    }
  },

  /* 40 */
  {
    "_id" : "529715da09a5db1f2d00000b",
    "wallet" : {
      "currency" : "EUR"
    }
  },

  /* 41 */
  {
    "_id" : "529730d7e4b95a924c00001d",
    "wallet" : {
      "currency" : "EUR"
    }
  },

  /* 42 */
  {
    "_id" : "52975afce4b95a924c000022",
    "wallet" : {
      "currency" : "EUR"
    }
  },

  /* 43 */
  {
    "_id" : "52976e01bc0c5b9e50000003",
    "wallet" : {
      "currency" : "EUR"
    }
  },

  /* 44 */
  {
    "_id" : "529773bebc0c5b9e50000012",
    "wallet" : {
      "currency" : "EUR"
    }
  },

  /* 45 */
  {
    "_id" : "52977503c361d04a33000008",
    "wallet" : {
      "currency" : "EUR"
    }
  },

  /* 46 */
  {
    "_id" : "5297751abc0c5b9e50000014",
    "wallet" : {
      "currency" : "EUR"
    }
  },

  /* 47 */
  {
    "_id" : "529775d3c361d04a33000009",
    "wallet" : {
      "currency" : "EUR"
    }
  },

  /* 48 */
  {
    "_id" : "52977620bc0c5b9e50000018",
    "wallet" : {
      "currency" : "EUR"
    }
  },

  /* 49 */
  {
    "_id" : "52977645c361d04a3300000e",
    "wallet" : {
      "currency" : "EUR"
    }
  },

  /* 50 */
  {
    "_id" : "52977a6ec361d04a33000011",
    "wallet" : {
      "currency" : "EUR"
    }
  },

  /* 51 */
  {
    "_id" : "52977dba1c696bbb50000004",
    "wallet" : {
      "currency" : "EUR"
    }
  },

  /* 52 */
  {
    "_id" : "5297ca60e71a7e6b3300001e",
    "wallet" : {
      "currency" : "EUR"
    }
  },

  /* 53 */
  {
    "_id" : "5297e13ae71a7e6b33000021",
    "wallet" : {
      "currency" : "EUR"
    }
  },

  /* 54 */
  {
    "_id" : "52985f541c696bbb50000022",
    "wallet" : {
      "currency" : "EUR"
    }
  },

  /* 55 */
  {
    "_id" : "52986fc296c8ab7b37000003",
    "wallet" : {
      "currency" : "EUR"
    }
  },

  /* 56 */
  {
    "_id" : "529870d1d514ef9b54000007",
    "wallet" : {
      "currency" : "EUR"
    }
  },

  /* 57 */
  {
    "_id" : "529878c896c8ab7b37000006",
    "wallet" : {
      "currency" : "EUR"
    }
  },

  /* 58 */
  {
    "_id" : "529890e7cc76376f56000007",
    "wallet" : {
      "currency" : "EUR"
    }
  },

  /* 59 */
  {
    "_id" : "529893cecc76376f5600000b",
    "wallet" : {
      "currency" : "EUR"
    }
  },

  /* 60 */
  {
    "_id" : "52989d0c35c27d0b3a000024",
    "wallet" : {
      "currency" : "EUR"
    }
  },

  /* 61 */
  {
    "_id" : "529c4a8f35c27d0b3a000077",
    "wallet" : {
      "currency" : "EUR"
    }
  },

  /* 62 */
  {
    "_id" : "529c60dbcc76376f560000a8",
    "wallet" : {
      "currency" : "EUR"
    }
  },

  /* 63 */
  {
    "_id" : "529c71b7cc76376f560000b6",
    "wallet" : {
      "currency" : "EUR"
    }
  },

  /* 64 */
  {
    "_id" : "529cdae90c0e972b45000005",
    "wallet" : {
      "currency" : "EUR"
    }
  },

  /* 65 */
  {
    "_id" : "529d9db00c0e972b45000024",
    "wallet" : {
      "currency" : "EUR"
    }
  },

  /* 66 */
  {
    "_id" : "529dab9e0c0e972b45000034",
    "wallet" : {
      "currency" : "EUR"
    }
  },

  /* 67 */
  {
    "_id" : "529daf770c0e972b45000035",
    "wallet" : {
      "currency" : "EUR"
    }
  },

  /* 68 */
  {
    "_id" : "52a09ef390b8b4446d000034",
    "wallet" : {
      "currency" : "EUR"
    }
  },

  /* 69 */
  {
    "_id" : "52a0a37190b8b4446d000036",
    "wallet" : {
      "currency" : "EUR"
    }
  },

  /* 70 */
  {
    "_id" : "52a5c0300032551f54000016",
    "wallet" : {
      "currency" : "EUR"
    }
  },

  /* 71 */
  {
    "_id" : "52a63e46094af5b459000004",
    "wallet" : {
      "currency" : "EUR"
    }
  },

  /* 72 */
  {
    "_id" : "52a98398c0bfb0936200000d",
    "wallet" : {
      "currency" : "EUR"
    }
  },

  /* 73 */
  {
    "_id" : "52aad2c1c0bfb0936200003d",
    "wallet" : {
      "currency" : "EUR"
    }
  },

  /* 74 */
  {
    "_id" : "52b173b3d514373c7f000003",
    "wallet" : {
      "currency" : "EUR"
    }
  },

  /* 75 */
  {
    "_id" : "52bd4f38398d1c8f12000008",
    "wallet" : {
      "currency" : "EUR"
    }
  },

  /* 76 */
  {
    "_id" : "52c58a97a519b3e11f00000b",
    "wallet" : {
      "currency" : "EUR"
    }
  },

  /* 77 */
  {
    "_id" : "52d3a19e70e1f71d40000011",
    "wallet" : {
      "currency" : "EUR"
    }
  },

  /* 78 */
  {
    "_id" : "52d3cf8270e1f71d40000017",
    "wallet" : {
      "currency" : "EUR"
    }
  },

  /* 79 */
  {
    "_id" : "52d3ec0870e1f71d40000020",
    "wallet" : {
      "currency" : "EUR"
    }
  },

  /* 80 */
  {
    "_id" : "52d55a8c383ba42362000014",
    "wallet" : {
      "currency" : "EUR"
    }
  },

  /* 81 */
  {
    "_id" : "52d80ca3f3bfc04d77000011",
    "wallet" : {
      "currency" : "EUR"
    }
  },

  /* 82 */
  {
    "_id" : "52d869c4dc2554835d00005c",
    "wallet" : {
      "currency" : "EUR"
    }
  },

  /* 83 */
  {
    "_id" : "52d915eef3bfc04d7700004d",
    "wallet" : {
      "currency" : "EUR"
    }
  },

  /* 84 */
  {
    "_id" : "52da68ef8a646f5161000008",
    "wallet" : {
      "currency" : "EUR"
    }
  },

  /* 85 */
  {
    "_id" : "52dd68eb8166121a7b00001c",
    "wallet" : {
      "currency" : "EUR"
    }
  },

  /* 86 */
  {
    "_id" : "52dfae29f88e770803000011",
    "wallet" : {
      "currency" : "EUR"
    }
  },

  /* 87 */
  {
    "_id" : "52e7a809196768cd15000059",
    "wallet" : {
      "currency" : "EUR"
    }
  },

  /* 88 */
  {
    "_id" : "52e8f49c839143df41000003",
    "wallet" : {
      "currency" : "EUR"
    }
  },

  /* 89 */
  {
    "_id" : "52ea6a9c839143df41000043",
    "wallet" : {
      "currency" : "EUR"
    }
  },

  /* 90 */
  {
    "_id" : "52eb947f58c7a1512900001d",
    "wallet" : {
      "currency" : "EUR"
    }
  },

  /* 91 */
  {
    "_id" : "52ed3c3958c7a15129000023",
    "wallet" : {
      "currency" : "EUR"
    }
  },

  /* 92 */
  {
    "_id" : "52efe710facc46b646000122",
    "wallet" : {
      "currency" : "EUR"
    }
  },

  /* 93 */
  {
    "_id" : "52f02ea9facc46b646000133",
    "wallet" : {
      "currency" : "EUR"
    }
  },

  /* 94 */
  {
    "_id" : "52f1ff6b2f5504955400001c",
    "wallet" : {
      "currency" : "EUR"
    }
  },

  /* 95 */
  {
    "_id" : "52f4ec2015ac39443b00006d",
    "wallet" : {
      "currency" : "EUR"
    }
  },

  /* 96 */
  {
    "_id" : "52fa576ffbd2483564000003",
    "wallet" : {
      "currency" : "EUR"
    }
  },

  /* 97 */
  {
    "_id" : "52fb4bd7fbd2483564000017",
    "wallet" : {
      "currency" : "EUR"
    }
  },

  /* 98 */
  {
    "_id" : "52fb9c7bfbd248356400002e",
    "wallet" : {
      "currency" : "EUR"
    }
  },

  /* 99 */
  {
    "_id" : "52fbe2b4fbd248356400003e",
    "wallet" : {
      "currency" : "EUR"
    }
  },

  /* 100 */
  {
    "_id" : "52fc7c4f15ac39443b0000f2",
    "wallet" : {
      "currency" : "EUR"
    }
  },

  /* 101 */
  {
    "_id" : "52fc8abf15ac39443b0000fe",
    "wallet" : {
      "currency" : "EUR"
    }
  },

  /* 102 */
  {
    "_id" : "52fe3fe243f4b72450000004",
    "wallet" : {
      "currency" : "EUR"
    }
  },

  /* 103 */
  {
    "_id" : "52fe43b69a5933666d000005",
    "wallet" : {
      "currency" : "EUR"
    }
  },

  /* 104 */
  {
    "_id" : "52ff7c0b9a5933666d000017",
    "wallet" : {
      "currency" : "EUR"
    }
  },

  /* 105 */
  {
    "_id" : "53033d5cd59493547200000d",
    "wallet" : {
      "currency" : "EUR"
    }
  },

  /* 106 */
  {
    "_id" : "5303aec7bb51dd175500002b",
    "wallet" : {
      "currency" : "EUR"
    }
  },

  /* 107 */
  {
    "_id" : "53050d8b68c525cf78000007",
    "wallet" : {
      "currency" : "EUR"
    }
  },

  /* 108 */
  {
    "_id" : "530533e48fa512cd5a000005",
    "wallet" : {
      "currency" : "EUR"
    }
  },

  /* 109 */
  {
    "_id" : "53060f188fa512cd5a000023",
    "wallet" : {
      "currency" : "EUR"
    }
  },

  /* 110 */
  {
    "_id" : "5306320b8fa512cd5a00002f",
    "wallet" : {
      "currency" : "EUR"
    }
  },

  /* 111 */
  {
    "_id" : "53065a8a8fa512cd5a00003a",
    "wallet" : {
      "currency" : "EUR"
    }
  },

  /* 112 */
  {
    "_id" : "5306732980f5302e7b000024",
    "wallet" : {
      "currency" : "EUR"
    }
  },

  /* 113 */
  {
    "_id" : "530b2add40bef30f67000028",
    "wallet" : {
      "currency" : "EUR"
    }
  },

  /* 114 */
  {
    "_id" : "530b982f542bfcba05000028",
    "wallet" : {
      "currency" : "EUR"
    }
  },

  /* 115 */
  {
    "_id" : "530c6980542bfcba05000037",
    "wallet" : {
      "currency" : "EUR"
    }
  },

  /* 116 */
  {
    "_id" : "530dae63542bfcba05000074",
    "wallet" : {
      "currency" : "EUR"
    }
  },

  /* 117 */
  {
    "_id" : "53107418542bfcba050000be",
    "wallet" : {
      "currency" : "EUR"
    }
  },

  /* 118 */
  {
    "_id" : "531624f240bef30f670000ce",
    "wallet" : {
      "currency" : "EUR"
    }
  },

  /* 119 */
  {
    "_id" : "53165773542bfcba050000ec",
    "wallet" : {
      "currency" : "EUR"
    }
  },

  /* 120 */
  {
    "_id" : "53172225e947572414000016",
    "wallet" : {
      "currency" : "EUR"
    }
  },

  /* 121 */
  {
    "_id" : "5317428d40bef30f670000e4",
    "wallet" : {
      "currency" : "EUR"
    }
  },

  /* 122 */
  {
    "_id" : "53176bd9e94757241400002c",
    "wallet" : {
      "currency" : "EUR"
    }
  },

  /* 123 */
  {
    "_id" : "531de6b5d72654242c000007",
    "wallet" : {
      "currency" : "EUR"
    }
  },

  /* 124 */
  {
    "_id" : "531deb06eee2edcf0e000016",
    "wallet" : {
      "currency" : "EUR"
    }
  },

  /* 125 */
  {
    "_id" : "531e27ebeee2edcf0e00002c",
    "wallet" : {
      "currency" : "EUR"
    }
  },

  /* 126 */
  {
    "_id" : "531f3eaceee2edcf0e00003b",
    "wallet" : {
      "currency" : "EUR"
    }
  },

  /* 127 */
  {
    "_id" : "532023a3eee2edcf0e000040",
    "wallet" : {
      "currency" : "USD"
    }
  },

  /* 128 */
  {
    "_id" : "53204fa7eee2edcf0e00004f",
    "wallet" : {
      "currency" : "EUR"
    }
  },

  /* 129 */
  {
    "_id" : "5320b27784a958ba3100001a",
    "wallet" : {
      "currency" : "EUR"
    }
  },

  /* 130 */
  {
    "_id" : "53297b7e4b712fad39000069",
    "wallet" : {
      "currency" : "EUR"
    }
  },

  /* 131 */
  {
    "_id" : "5329a160eac02d8021000006",
    "wallet" : {
      "currency" : "EUR"
    }
  },

  /* 132 */
  {
    "_id" : "533182956b5ae89f7600000f",
    "wallet" : {
      "currency" : "EUR"
    }
  },

  /* 133 */
  {
    "_id" : "5331839690146ccd73000005",
    "wallet" : {
      "currency" : "EUR"
    }
  },

  /* 134 */
  {
    "_id" : "5332e3738730548e16000003",
    "wallet" : {
      "currency" : "EUR"
    }
  },

  /* 135 */
  {
    "_id" : "5342cf6cc51d364a7e000011",
    "wallet" : {
      "currency" : "EUR"
    }
  },

  /* 136 */
  {
    "_id" : "53444f728af532b11a000051",
    "wallet" : {
      "currency" : "EUR"
    }
  },

  /* 137 */
  {
    "_id" : "534506b7307a1ad02c00007d",
    "wallet" : {
      "currency" : "EUR"
    }
  },

  /* 138 */
  {
    "_id" : "53451ac88af532b11a000061",
    "wallet" : {
      "currency" : "EUR"
    }
  },

  /* 139 */
  {
    "_id" : "5347a0397b7909824b000008",
    "wallet" : {
      "currency" : "EUR"
    }
  },

  /* 140 */
  {
    "_id" : "5347b28f7b7909824b00000b",
    "wallet" : {
      "currency" : "EUR"
    }
  },

  /* 141 */
  {
    "_id" : "53497173a5b99df14300002f",
    "wallet" : {
      "currency" : "EUR"
    }
  },

  /* 142 */
  {
    "_id" : "534981187b7909824b000013",
    "wallet" : {
      "currency" : "EUR"
    }
  },

  /* 143 */
  {
    "_id" : "534e5d79b01aa8f83400000c",
    "wallet" : {
      "currency" : "EUR"
    }
  },

  /* 144 */
  {
    "_id" : "534e5fcfaa3911e571000018",
    "wallet" : {
      "currency" : "EUR"
    }
  },

  /* 145 */
  {
    "_id" : "534e6d7685ea754753000004",
    "wallet" : {
      "currency" : "EUR"
    }
  },

  /* 146 */
  {
    "_id" : "5356301e923bd38c22000004",
    "wallet" : {
      "currency" : "EUR"
    }
  },

  /* 147 */
  {
    "_id" : "535681f8e59ee21b59000004",
    "wallet" : {
      "currency" : "EUR"
    }
  },

  /* 148 */
  {
    "_id" : "5356a3739917c1175f000008",
    "wallet" : {
      "currency" : "USD"
    }
  },

  /* 149 */
  {
    "_id" : "5356cd369917c1175f00000b",
    "wallet" : {
      "currency" : "EUR"
    }
  },

  /* 150 */
  {
    "_id" : "5358f3999917c1175f00003f",
    "wallet" : {
      "currency" : "EUR"
    }
  },

  /* 151 */
  {
    "_id" : "535f6c6887d91e9153000006",
    "wallet" : {
      "currency" : "EUR"
    }
  },

  /* 152 */
  {
    "_id" : "5361f37555728e8363000033",
    "wallet" : {
      "currency" : "EUR"
    }
  },

  /* 153 */
  {
    "_id" : "5361f9b8550e6b037100003f",
    "wallet" : {
      "currency" : "EUR"
    }
  },

  /* 154 */
  {
    "_id" : "536333e655728e8363000040",
    "wallet" : {
      "currency" : "EUR"
    }
  },

  /* 155 */
  {
    "_id" : "5368c5b4d086a43635000018",
    "wallet" : {
      "currency" : "EUR"
    }
  },

  /* 156 */
  {
    "_id" : "5368ce46d086a4363500001a",
    "wallet" : {
      "currency" : "EUR"
    }
  },

  /* 157 */
  {
    "_id" : "536a5ba3b9d2e0bc37000039",
    "wallet" : {
      "currency" : "EUR"
    }
  },

  /* 158 */
  {
    "_id" : "536a79f3d086a4363500003b",
    "wallet" : {
      "currency" : "EUR"
    }
  },

  /* 159 */
  {
    "_id" : "536ba939d086a43635000059",
    "wallet" : {
      "currency" : "EUR"
    }
  },

  /* 160 */
  {
    "_id" : "537241ae1834d5a254000009",
    "wallet" : {
      "currency" : "USD"
    }
  },

  /* 161 */
  {
    "_id" : "53733a5dde9db96233000038",
    "wallet" : {
      "currency" : "EUR"
    }
  },

  /* 162 */
  {
    "_id" : "5373732ede9db96233000041",
    "wallet" : {
      "currency" : "EUR"
    }
  },

  /* 163 */
  {
    "_id" : "5374c65e1834d5a254000011",
    "wallet" : {
      "currency" : "EUR"
    }
  },

  /* 164 */
  {
    "_id" : "5383474f1f604f990b000005",
    "wallet" : {
      "currency" : "EUR"
    }
  },

  /* 165 */
  {
    "_id" : "5387039d58b195c061000038",
    "wallet" : {
      "currency" : "EUR"
    }
  },

  /* 166 */
  {
    "_id" : "5387208ecf30908a2e00002f",
    "wallet" : {
      "currency" : "EUR"
    }
  },

  /* 167 */
  {
    "_id" : "5388520158b195c06100007a",
    "wallet" : {
      "currency" : "EUR"
    }
  },

  /* 168 */
  {
    "_id" : "5388d11dca4c555112000008",
    "wallet" : {
      "currency" : "EUR"
    }
  },

  /* 169 */
  {
    "_id" : "538c95c0f66c1bb14d000017",
    "wallet" : {
      "currency" : "EUR"
    }
  },

  /* 170 */
  {
    "_id" : "538f471c242648b463000008",
    "wallet" : {
      "currency" : "EUR"
    }
  },

  /* 171 */
  {
    "_id" : "53939dab47d954e026000018",
    "wallet" : {
      "currency" : "EUR"
    }
  },

  /* 172 */
  {
    "_id" : "539569caa868827f0c000018",
    "wallet" : {
      "currency" : "EUR"
    }
  },

  /* 173 */
  {
    "_id" : "5396dcbd3bd752350c00004f",
    "wallet" : {
      "currency" : "EUR"
    }
  },

  /* 174 */
  {
    "_id" : "53982b9c3bd752350c00007e",
    "wallet" : {
      "currency" : "EUR"
    }
  },

  /* 175 */
  {
    "_id" : "539855293bd752350c00008a",
    "wallet" : {
      "currency" : "EUR"
    }
  },

  /* 176 */
  {
    "_id" : "539b009409b22cc25b000df2",
    "wallet" : {
      "currency" : "EUR"
    }
  },

  /* 177 */
  {
    "_id" : "53a00186b65b3c1b2a00000f",
    "wallet" : {
      "currency" : "EUR"
    }
  },

  /* 178 */
  {
    "_id" : "53a19280c3194bf14a000037",
    "wallet" : {
      "currency" : "EUR"
    }
  },

  /* 179 */
  {
    "_id" : "53a3f2ec5c9fed7e72000007",
    "wallet" : {
      "currency" : "EUR"
    }
  },

  /* 180 */
  {
    "_id" : "53a42e0f4cd4d52e78000196",
    "wallet" : {
      "currency" : "EUR"
    }
  },

  /* 181 */
  {
    "_id" : "53ad24a3080852961b0008c4",
    "wallet" : {
      "currency" : "EUR"
    }
  },

  /* 182 */
  {
    "_id" : "53ad344267890b1a1f00086e",
    "wallet" : {
      "currency" : "EUR"
    }
  },

  /* 183 */
  {
    "_id" : "53b12995080852961b000b62",
    "wallet" : {
      "currency" : "EUR"
    }
  },

  /* 184 */
  {
    "_id" : "53b1731611ef2ae438000004",
    "wallet" : {
      "currency" : "EUR"
    }
  },

  /* 185 */
  {
    "_id" : "53b188ffa3196ab53f000004",
    "wallet" : {
      "currency" : "EUR"
    }
  },

  /* 186 */
  {
    "_id" : "53b190a2a3196ab53f000008",
    "wallet" : {
      "currency" : "EUR"
    }
  },

  /* 187 */
  {
    "_id" : "53b29704810721423000000b",
    "wallet" : {
      "currency" : "EUR"
    }
  },

  /* 188 */
  {
    "_id" : "53b2d4c2810721423000001a",
    "wallet" : {
      "currency" : "EUR"
    }
  },

  /* 189 */
  {
    "_id" : "53b3e302864d0fea5a00002d",
    "wallet" : {
      "currency" : "EUR"
    }
  },

  /* 190 */
  {
    "_id" : "53b435d63286163501000006",
    "wallet" : {
      "currency" : "EUR"
    }
  },

  /* 191 */
  {
    "_id" : "53b53880c0255c341c000025",
    "wallet" : {
      "currency" : "EUR"
    }
  },

  /* 192 */
  {
    "_id" : "53b66b51c0255c341c00004f",
    "wallet" : {
      "currency" : "EUR"
    }
  },

  /* 193 */
  {
    "_id" : "53bd05a57636808b350000ac",
    "wallet" : {
      "currency" : "USD"
    }
  },

  /* 194 */
  {
    "_id" : "53bd46f57636808b350000d9",
    "wallet" : {
      "currency" : "EUR"
    }
  },

  /* 195 */
  {
    "_id" : "53bd570f7636808b350000e2",
    "wallet" : {
      "currency" : "EUR"
    }
  },

  /* 196 */
  {
    "_id" : "53bd76f414f74f732e000009",
    "wallet" : {
      "currency" : "USD"
    }
  },

  /* 197 */
  {
    "_id" : "53be4f4323e40e190200001d",
    "wallet" : {
      "currency" : "EUR"
    }
  },

  /* 198 */
  {
    "_id" : "53bedb7514f74f732e000062",
    "wallet" : {
      "currency" : "USD"
    }
  },

  /* 199 */
  {
    "_id" : "53bf9bf723e40e19020000ab",
    "wallet" : {
      "currency" : "EUR"
    }
  },

  /* 200 */
  {
    "_id" : "53c3bd3014f74f732e0000c9",
    "wallet" : {
      "currency" : "EUR"
    }
  },

  /* 201 */
  {
    "_id" : "53c65b283010fdfb48000017",
    "wallet" : {
      "currency" : "EUR"
    }
  },

  /* 202 */
  {
    "_id" : "53c69b1c64ce904e77000014",
    "wallet" : {
      "currency" : "EUR"
    }
  },

  /* 203 */
  {
    "_id" : "53c7dbcb78e8268c4f000046",
    "wallet" : {
      "currency" : "EUR"
    }
  },

  /* 204 */
  {
    "_id" : "53c8de564dc6d6261c000022",
    "wallet" : {
      "currency" : "EUR"
    }
  },

  /* 205 */
  {
    "_id" : "53c8e35a4dc6d6261c000198",
    "wallet" : {
      "currency" : "EUR"
    }
  },

  /* 206 */
  {
    "_id" : "53c90debb76566915f00000c",
    "wallet" : {
      "currency" : "EUR"
    }
  },

  /* 207 */
  {
    "_id" : "53ce713633d4f0824a000039",
    "wallet" : {
      "currency" : "EUR"
    }
  },

  /* 208 */
  {
    "_id" : "53cfe2ca4165a53e4d000011",
    "wallet" : {
      "currency" : "USD"
    }
  },

  /* 209 */
  {
    "_id" : "53d24c2f906ad83860000021",
    "wallet" : {
      "currency" : "EUR"
    }
  },

  /* 210 */
  {
    "_id" : "53d6691fdbe30e4a0f000074",
    "wallet" : {
      "currency" : "EUR"
    }
  },

  /* 211 */
  {
    "_id" : "53d7c287dbe30e4a0f0000a5",
    "wallet" : {
      "currency" : "EUR"
    }
  },

  /* 212 */
  {
    "_id" : "53d901dadbe30e4a0f0000dc",
    "wallet" : {
      "currency" : "EUR"
    }
  },

  /* 213 */
  {
    "_id" : "53e1f2e7b0db515c6a0000bc",
    "wallet" : {
      "currency" : "EUR"
    }
  },

  /* 214 */
  {
    "_id" : "53e488808f2f93a775000004",
    "wallet" : {
      "currency" : "EUR"
    }
  },

  /* 215 */
  {
    "_id" : "53e49736539150f40a00000c",
    "wallet" : {
      "currency" : "EUR"
    }
  },

  /* 216 */
  {
    "_id" : "53e4f43806e88dbd15000006",
    "wallet" : {
      "currency" : "USD"
    }
  },

  /* 217 */
  {
    "_id" : "53e88dea3c5312ae5f000004",
    "wallet" : {
      "currency" : "EUR"
    }
  },

  /* 218 */
  {
    "_id" : "53e8a15e844335702a000019",
    "wallet" : {
      "currency" : "EUR"
    }
  },

  /* 219 */
  {
    "_id" : "53e92690844335702a00003e",
    "wallet" : {
      "currency" : "USD"
    }
  },

  /* 220 */
  {
    "_id" : "53ea30ff844335702a000053",
    "wallet" : {
      "currency" : "USD"
    }
  },

  /* 221 */
  {
    "_id" : "53eceb058a5860b16000000a",
    "wallet" : {
      "currency" : "EUR"
    }
  },

  /* 222 */
  {
    "_id" : "53ed43d5dac284db61000016",
    "wallet" : {
      "currency" : "EUR"
    }
  },

  /* 223 */
  {
    "_id" : "53f6458635c4faa909000028",
    "wallet" : {
      "currency" : "USD"
    }
  },

  /* 224 */
  {
    "_id" : "53fb57ac35c4faa9090000a4",
    "wallet" : {
      "currency" : "EUR"
    }
  },

  /* 225 */
  {
    "_id" : "53ff1df45562ab9637000005",
    "wallet" : {
      "currency" : "EUR"
    }
  },

  /* 226 */
  {
    "_id" : "5400389ee9664a1c3b000016",
    "wallet" : {
      "currency" : "EUR"
    }
  },

  /* 227 */
  {
    "_id" : "54011fdbf86fc8177600000c",
    "wallet" : {
      "currency" : "EUR"
    }
  },

  /* 228 */
  {
    "_id" : "540593ccf86fc81776000043",
    "wallet" : {
      "currency" : "EUR"
    }
  },

  /* 229 */
  {
    "_id" : "54097387f86fc8177600009a",
    "wallet" : {
      "currency" : "EUR"
    }
  },

  /* 230 */
  {
    "_id" : "54099876f86fc817760000ae",
    "wallet" : {
      "currency" : "EUR"
    }
  },

  /* 231 */
  {
    "_id" : "54103222f66446863800000f",
    "wallet" : {
      "currency" : "EUR"
    }
  },

  /* 232 */
  {
    "_id" : "54103586f664468638000033",
    "wallet" : {
      "currency" : "EUR"
    }
  },

  /* 233 */
  {
    "_id" : "5412caabf449c9063c000031",
    "wallet" : {
      "currency" : "EUR"
    }
  },

  /* 234 */
  {
    "_id" : "5416aa70f449c9063c00006c",
    "wallet" : {
      "currency" : "USD"
    }
  },

  /* 235 */
  {
    "_id" : "541847a478b35d177800009b",
    "wallet" : {
      "currency" : "EUR"
    }
  },

  /* 236 */
  {
    "_id" : "541965bdf4970267020000d8",
    "wallet" : {
      "currency" : "EUR"
    }
  },

  /* 237 */
  {
    "_id" : "541bf08f3f28d8570100001f",
    "wallet" : {
      "currency" : "EUR"
    }
  },

  /* 238 */
  {
    "_id" : "541bfbcf3f28d85701000035",
    "wallet" : {
      "currency" : "EUR"
    }
  },

  /* 239 */
  {
    "_id" : "541c21c58cf222fe65000051",
    "wallet" : {
      "currency" : "EUR"
    }
  },

  /* 240 */
  {
    "_id" : "5421a0de0201c46372000052",
    "wallet" : {
      "currency" : "USD"
    }
  },

  /* 241 */
  {
    "_id" : "54230cf60201c463720000bc",
    "wallet" : {
      "currency" : "EUR"
    }
  },

  /* 242 */
  {
    "_id" : "54242b008fb6a2ba35000111",
    "wallet" : {
      "currency" : "EUR"
    }
  },

  /* 243 */
  {
    "_id" : "542470e6fc12c22211000009",
    "wallet" : {
      "currency" : "EUR"
    }
  },

  /* 244 */
  {
    "_id" : "5425889f0cfb7d9a06000017",
    "wallet" : {
      "currency" : "USD"
    }
  },

  /* 245 */
  {
    "_id" : "542c23abdd22adf00400003f",
    "wallet" : {
      "currency" : "EUR"
    }
  },

  /* 246 */
  {
    "_id" : "542d2b13fca2005850000007",
    "wallet" : {
      "currency" : "EUR"
    }
  },

  /* 247 */
  {
    "_id" : "542e8d0dfca2005850000045",
    "wallet" : {
      "currency" : "EUR"
    }
  },

  /* 248 */
  {
    "_id" : "54325c90fca2005850000066",
    "wallet" : {
      "currency" : "EUR"
    }
  },

  /* 249 */
  {
    "_id" : "5433b8f804281d784e00017f",
    "wallet" : {
      "currency" : "USD"
    }
  },

  /* 250 */
  {
    "_id" : "5434540ae069284961000024",
    "wallet" : {
      "currency" : "USD"
    }
  },

  /* 251 */
  {
    "_id" : "54350a9be069284961000030",
    "wallet" : {
      "currency" : "EUR"
    }
  },

  /* 252 */
  {
    "_id" : "54354c7ee069284961000050",
    "wallet" : {
      "currency" : "EUR"
    }
  },

  /* 253 */
  {
    "_id" : "543bea56f3e087787e0000f7",
    "wallet" : {
      "currency" : "EUR"
    }
  },

  /* 254 */
  {
    "_id" : "543cd953f3e087787e000118",
    "wallet" : {
      "currency" : "USD"
    }
  },

  /* 255 */
  {
    "_id" : "543d38bbf3e087787e00013e",
    "wallet" : {
      "currency" : "EUR"
    }
  },

  /* 256 */
  {
    "_id" : "543eb207101020b959000027",
    "wallet" : {
      "currency" : "USD"
    }
  },

  /* 257 */
  {
    "_id" : "543f7884fb9b8f6423000011",
    "wallet" : {
      "currency" : "USD"
    }
  },

  /* 258 */
  {
    "_id" : "543ff444fb9b8f6423000024",
    "wallet" : {
      "currency" : "EUR"
    }
  },

  /* 259 */
  {
    "_id" : "5440d14efb9b8f642300003c",
    "wallet" : {
      "currency" : "EUR"
    }
  },

  /* 260 */
  {
    "_id" : "5444c9fd2d62af15290004e7",
    "wallet" : {
      "currency" : "USD"
    }
  },

  /* 261 */
  {
    "_id" : "544696f9fb9b8f64230000ee",
    "wallet" : {
      "currency" : "USD"
    }
  },

  /* 262 */
  {
    "_id" : "5448d498101020b959000127",
    "wallet" : {
      "currency" : "EUR"
    }
  },

  /* 263 */
  {
    "_id" : "544919cd101020b95900013c",
    "wallet" : {
      "currency" : "EUR"
    }
  },

  /* 264 */
  {
    "_id" : "544fc58e9a2daca60e000026",
    "wallet" : {
      "currency" : "EUR"
    }
  },

  /* 265 */
  {
    "_id" : "545137f36a0a90e31d000082",
    "wallet" : {
      "currency" : "EUR"
    }
  },

  /* 266 */
  {
    "_id" : "54536469ae4361132d000090",
    "wallet" : {
      "currency" : "EUR"
    }
  },

  /* 267 */
  {
    "_id" : "545367ac6a0a90e31d0000df",
    "wallet" : {
      "currency" : "USD"
    }
  },

  /* 268 */
  {
    "_id" : "5453c33c6a0a90e31d0000fe",
    "wallet" : {
      "currency" : "EUR"
    }
  },

  /* 269 */
  {
    "_id" : "545753a2ae4361132d0000ee",
    "wallet" : {
      "currency" : "EUR"
    }
  },

  /* 270 */
  {
    "_id" : "54578e3d12d8ec9766000006",
    "wallet" : {
      "currency" : "USD"
    }
  },

  /* 271 */
  {
    "_id" : "5457a8befb38ae246b000006",
    "wallet" : {
      "currency" : "EUR"
    }
  },

  /* 272 */
  {
    "_id" : "5457b1c9fb4e1f417500001b",
    "wallet" : {
      "currency" : "EUR"
    }
  },

  /* 273 */
  {
    "_id" : "5457b549d30016906d000014",
    "wallet" : {
      "currency" : "EUR"
    }
  },

  /* 274 */
  {
    "_id" : "5457bb57d30016906d000016",
    "wallet" : {
      "currency" : "EUR"
    }
  },

  /* 275 */
  {
    "_id" : "5457bf1615a741434d000022",
    "wallet" : {
      "currency" : "USD"
    }
  },

  /* 276 */
  {
    "_id" : "5457c311be491d6252000007",
    "wallet" : {
      "currency" : "EUR"
    }
  },

  /* 277 */
  {
    "_id" : "5457cb7e6568a54776000007",
    "wallet" : {
      "currency" : "USD"
    }
  },

  /* 278 */
  {
    "_id" : "5457d59866570b207a000007",
    "wallet" : {
      "currency" : "USD"
    }
  },

  /* 279 */
  {
    "_id" : "5457ee5e66570b207a000023",
    "wallet" : {
      "currency" : "EUR"
    }
  },

  /* 280 */
  {
    "_id" : "5457f92bd44d62677e000014",
    "wallet" : {
      "currency" : "USD"
    }
  },

  /* 281 */
  {
    "_id" : "5458892cdbfc88900300000b",
    "wallet" : {
      "currency" : "USD"
    }
  },

  /* 282 */
  {
    "_id" : "5458aee5953f004a73000030",
    "wallet" : {
      "currency" : "EUR"
    }
  },

  /* 283 */
  {
    "_id" : "5458bcd7c49a9b197600001e",
    "wallet" : {
      "currency" : "EUR"
    }
  },

  /* 284 */
  {
    "_id" : "5458bdbe0372c0f877000007",
    "wallet" : {
      "currency" : "EUR"
    }
  },

  /* 285 */
  {
    "_id" : "5458ec3e60842bbd2000000d",
    "wallet" : {
      "currency" : "EUR"
    }
  },

  /* 286 */
  {
    "_id" : "5459003523a4cb686a000007",
    "wallet" : {
      "currency" : "EUR"
    }
  },

  /* 287 */
  {
    "_id" : "5459013023a4cb686a00000b",
    "wallet" : {
      "currency" : "EUR"
    }
  },

  /* 288 */
  {
    "_id" : "54590583965982dc2f000009",
    "wallet" : {
      "currency" : "EUR"
    }
  },

  /* 289 */
  {
    "_id" : "545908c1bf9baec506000022",
    "wallet" : {
      "currency" : "EUR"
    }
  },

  /* 290 */
  {
    "_id" : "545946e12dd33a6035000009",
    "wallet" : {
      "currency" : "EUR"
    }
  },

  /* 291 */
  {
    "_id" : "545bea7aff467a561900000d",
    "wallet" : {
      "currency" : "EUR"
    }
  },

  /* 292 */
  {
    "_id" : "545c8d49ad8ca9465300000a",
    "wallet" : {
      "currency" : "EUR"
    }
  },

  /* 293 */
  {
    "_id" : "546230ab92f941712100003a",
    "wallet" : {
      "currency" : "EUR"
    }
  },

  /* 294 */
  {
    "_id" : "54624966c61f218678000007",
    "wallet" : {
      "currency" : "EUR"
    }
  },

  /* 295 */
  {
    "_id" : "54629552c61f218678000012",
    "wallet" : {
      "currency" : "EUR"
    }
  },

  /* 296 */
  {
    "_id" : "546330b2c61f218678000021",
    "wallet" : {
      "currency" : "USD"
    }
  },

  /* 297 */
  {
    "_id" : "5463538499c5462a5e00004a",
    "wallet" : {
      "currency" : "EUR"
    }
  },

  /* 298 */
  {
    "_id" : "54647802e53fa91f1b00003b",
    "wallet" : {
      "currency" : "USD"
    }
  },

  /* 299 */
  {
    "_id" : "5465c260a979027170000056",
    "wallet" : {
      "currency" : "EUR"
    }
  },

  /* 300 */
  {
    "_id" : "5465d69fa97902717000010a",
    "wallet" : {
      "currency" : "EUR"
    }
  },

  /* 301 */
  {
    "_id" : "54661444bbdd3ea45f000006",
    "wallet" : {
      "currency" : "EUR"
    }
  },

  /* 302 */
  {
    "_id" : "546b1abab323483a1000000f",
    "wallet" : {
      "currency" : "EUR"
    }
  },

  /* 303 */
  {
    "_id" : "546cc88d3f6035824a00002b",
    "wallet" : {
      "currency" : "EUR"
    }
  },

  /* 304 */
  {
    "_id" : "546db1d9f2f8048d1300006d",
    "wallet" : {
      "currency" : "USD"
    }
  },

  /* 305 */
  {
    "_id" : "546db2063f6035824a00003a",
    "wallet" : {
      "currency" : "EUR"
    }
  },

  /* 306 */
  {
    "_id" : "547246aca127531676000068",
    "wallet" : {
      "currency" : "EUR"
    }
  },

  /* 307 */
  {
    "_id" : "5474407623bc58480d000013",
    "wallet" : {
      "currency" : "USD"
    }
  },

  /* 308 */
  {
    "_id" : "5474bf60a1275316760009f3",
    "wallet" : {
      "currency" : "EUR"
    }
  },

  /* 309 */
  {
    "_id" : "5475c884a12753167600526d",
    "wallet" : {
      "currency" : "EUR"
    }
  },

  /* 310 */
  {
    "_id" : "5475f7e3a127531676006377",
    "wallet" : {
      "currency" : "EUR"
    }
  },

  /* 311 */
  {
    "_id" : "54775a31a127531676008b3c",
    "wallet" : {
      "currency" : "EUR"
    }
  },

  /* 312 */
  {
    "_id" : "54775df7aa77fc797b000030",
    "wallet" : {
      "currency" : "EUR"
    }
  },

  /* 313 */
  {
    "_id" : "547c5cdba12753167600dc71",
    "wallet" : {
      "currency" : "EUR"
    }
  },

  /* 314 */
  {
    "_id" : "547ee061a12753167600dd0f",
    "wallet" : {
      "currency" : "USD"
    }
  },

  /* 315 */
  {
    "_id" : "547f459ceeda6c054100003f",
    "wallet" : {
      "currency" : "EUR"
    }
  },

  /* 316 */
  {
    "_id" : "547f4ddd457d99216700003e",
    "wallet" : {
      "currency" : "EUR"
    }
  },

  /* 317 */
  {
    "_id" : "54815bda23bc58480d00dc06",
    "wallet" : {
      "currency" : "EUR"
    }
  },

  /* 318 */
  {
    "_id" : "5481a65023bc58480d00dc24",
    "wallet" : {
      "currency" : "EUR"
    }
  },

  /* 319 */
  {
    "_id" : "5485647ea12753167600dede",
    "wallet" : {
      "currency" : "EUR"
    }
  },

  /* 320 */
  {
    "_id" : "548724a8a12753167600df0b",
    "wallet" : {
      "currency" : "EUR"
    }
  },

  /* 321 */
  {
    "_id" : "548886431814449a17000031",
    "wallet" : {
      "currency" : "EUR"
    }
  },

  /* 322 */
  {
    "_id" : "54895a291814449a1700004d",
    "wallet" : {
      "currency" : "EUR"
    }
  },

  /* 323 */
  {
    "_id" : "54896ad223bc58480d00dcac",
    "wallet" : {
      "currency" : "USD"
    }
  },

  /* 324 */
  {
    "_id" : "5489bc6b23bc58480d00dcb6",
    "wallet" : {
      "currency" : "EUR"
    }
  },

  /* 325 */
  {
    "_id" : "548abc6ca12753167600df88",
    "wallet" : {
      "currency" : "EUR"
    }
  },

  /* 326 */
  {
    "_id" : "548c179523bc58480d00dcef",
    "wallet" : {
      "currency" : "EUR"
    }
  },

  /* 327 */
  {
    "_id" : "54901c3323bc58480d00dd36",
    "wallet" : {
      "currency" : "EUR"
    }
  },

  /* 328 */
  {
    "_id" : "549422125ab5576e5d000032",
    "wallet" : {
      "currency" : "EUR"
    }
  },

  /* 329 */
  {
    "_id" : "5497ecf966bf1dfa7600004d",
    "wallet" : {
      "currency" : "EUR"
    }
  },

  /* 330 */
  {
    "_id" : "549e2f4a5ab5576e5d0000a4",
    "wallet" : {
      "currency" : "EUR"
    }
  },

  /* 331 */
  {
    "_id" : "54a2ca335336771a66000076",
    "wallet" : {
      "currency" : "EUR"
    }
  },

  /* 332 */
  {
    "_id" : "54a69e9db38ed16c7c00005a",
    "wallet" : {
      "currency" : "USD"
    }
  },

  /* 333 */
  {
    "_id" : "54ad4fc25336771a660000d1",
    "wallet" : {
      "currency" : "USD"
    }
  },

  /* 334 */
  {
    "_id" : "54ae498f5336771a660000d6",
    "wallet" : {
      "currency" : "EUR"
    }
  },

  /* 335 */
  {
    "_id" : "54b3ebb805858acb02000010",
    "wallet" : {
      "currency" : "USD"
    }
  },

  /* 336 */
  {
    "_id" : "54b538165ab5576e5d00013a",
    "wallet" : {
      "currency" : "EUR"
    }
  },

  /* 337 */
  {
    "_id" : "54b54144a907bde635000019",
    "wallet" : {
      "currency" : "USD"
    }
  },

  /* 338 */
  {
    "_id" : "54b7849a5ab5576e5d000188",
    "wallet" : {
      "currency" : "EUR"
    }
  },

  /* 339 */
  {
    "_id" : "54b918fb7ca8d6f170000063",
    "wallet" : {
      "currency" : "USD"
    }
  },

  /* 340 */
  {
    "_id" : "54bccb925ab5576e5d0001b4",
    "wallet" : {
      "currency" : "USD"
    }
  },

  /* 341 */
  {
    "_id" : "54bd16d2be12cf2a5b0000c6",
    "wallet" : {
      "currency" : "USD"
    }
  },

  /* 342 */
  {
    "_id" : "54be35475ab5576e5d0001eb",
    "wallet" : {
      "currency" : "USD"
    }
  },

  /* 343 */
  {
    "_id" : "54be381fbe12cf2a5b0000f5",
    "wallet" : {
      "currency" : "USD"
    }
  },

  /* 344 */
  {
    "_id" : "54c2113abe12cf2a5b0001f1",
    "wallet" : {
      "currency" : "USD"
    }
  },

  /* 345 */
  {
    "_id" : "54c659905ab5576e5d0002c3",
    "wallet" : {
      "currency" : "USD"
    }
  },

  /* 346 */
  {
    "_id" : "54c89775be12cf2a5b000281",
    "wallet" : {
      "currency" : "EUR"
    }
  },

  /* 347 */
  {
    "_id" : "54c951feedee809f4400001f",
    "wallet" : {
      "currency" : "EUR"
    }
  },

  /* 348 */
  {
    "_id" : "54ca36f2edee809f4400004a",
    "wallet" : {
      "currency" : "EUR"
    }
  },

  /* 349 */
  {
    "_id" : "54d01ddaecfe6bbb23000097",
    "wallet" : {
      "currency" : "USD"
    }
  },

  /* 350 */
  {
    "_id" : "54d361fe79d77cd371000155",
    "wallet" : {
      "currency" : "USD"
    }
  },

  /* 351 */
  {
    "_id" : "54da3f72176f80334c00004a",
    "wallet" : {
      "currency" : "USD"
    }
  },

  /* 352 */
  {
    "_id" : "54dc6687e3824d331a00002b",
    "wallet" : {
      "currency" : "USD"
    }
  },

  /* 353 */
  {
    "_id" : "54dc68922ce6bd583200002f",
    "wallet" : {
      "currency" : "USD"
    }
  },

  /* 354 */
  {
    "_id" : "54ddbd7904a08a9f3c00005c",
    "wallet" : {
      "currency" : "EUR"
    }
  },

  /* 355 */
  {
    "_id" : "54dde67cfbdb9e6b66000031",
    "wallet" : {
      "currency" : "USD"
    }
  },

  /* 356 */
  {
    "_id" : "54e4a372ecfe6bbb2300019f",
    "wallet" : {
      "currency" : "EUR"
    }
  },

  /* 357 */
  {
    "_id" : "54e4a72b2dbd323972000029",
    "wallet" : {
      "currency" : "EUR"
    }
  },

  /* 358 */
  {
    "_id" : "54e4b7afecfe6bbb230001ad",
    "wallet" : {
      "currency" : "EUR"
    }
  },

  /* 359 */
  {
    "_id" : "54ec55ef57aa41be0b00020d",
    "wallet" : {
      "currency" : "USD"
    }
  },

  /* 360 */
  {
    "_id" : "54ec57e42dbd323972000230",
    "wallet" : {
      "currency" : "USD"
    }
  },

  /* 361 */
  {
    "_id" : "54f6b458fbdb9e6b660002ea",
    "wallet" : {
      "currency" : "EUR"
    }
  },

  /* 362 */
  {
    "_id" : "54f85cb2d766ec432d00001c",
    "wallet" : {
      "currency" : "USD"
    }
  },

  /* 363 */
  {
    "_id" : "54f97c8a99b66d040c00002f",
    "wallet" : {
      "currency" : "USD"
    }
  },

  /* 364 */
  {
    "_id" : "54f980a8d766ec432d000041",
    "wallet" : {
      "currency" : "USD"
    }
  },

  /* 365 */
  {
    "_id" : "54ff1a66f20f2f420f000059",
    "wallet" : {
      "currency" : "GBP"
    }
  },

  /* 366 */
  {
    "_id" : "54ffc7d1c34a31cb5900007b",
    "wallet" : {
      "currency" : "USD"
    }
  },

  /* 367 */
  {
    "_id" : "55001749c34a31cb5900008f",
    "wallet" : {
      "currency" : "USD"
    }
  },

  /* 368 */
  {
    "_id" : "5500ed37f20f2f420f000135",
    "wallet" : {
      "currency" : "EUR"
    }
  },

  /* 369 */
  {
    "_id" : "550937a6c8da28dd1c000036",
    "wallet" : {
      "currency" : "EUR"
    }
  },

  /* 370 */
  {
    "_id" : "55115a05f4213c5f1600001a",
    "wallet" : {
      "currency" : "EUR"
    }
  },

  /* 371 */
  {
    "_id" : "5511ca194f22343266000051",
    "wallet" : {
      "currency" : "USD"
    }
  },

  /* 372 */
  {
    "_id" : "551284449fa4ec2804000007",
    "wallet" : {
      "currency" : "EUR"
    }
  },

  /* 373 */
  {
    "_id" : "5512b0079fa4ec2804000023",
    "wallet" : {
      "currency" : "USD"
    }
  },

  /* 374 */
  {
    "_id" : "552293ff7d244f367f00006b",
    "wallet" : {
      "currency" : "EUR"
    }
  },

  /* 375 */
  {
    "_id" : "5523c751308c4e3f4d000009",
    "wallet" : {
      "currency" : "USD"
    }
  },

  /* 376 */
  {
    "_id" : "552bb6fd9717c4040a000020",
    "wallet" : {
      "currency" : "EUR"
    }
  },

  /* 377 */
  {
    "_id" : "552bb7229717c4040a000021",
    "wallet" : {
      "currency" : "EUR"
    }
  },

  /* 378 */
  {
    "_id" : "552d0a7f00c9eb234c0000a5",
    "wallet" : {
      "currency" : "EUR"
    }
  },

  /* 379 */
  {
    "_id" : "552fdd9cdda6f64512000012",
    "wallet" : {
      "currency" : "EUR"
    }
  },

  /* 380 */
  {
    "_id" : "5534f69570e75b8c7e00004a",
    "wallet" : {
      "currency" : "EUR"
    }
  },

  /* 381 */
  {
    "_id" : "553775846963caa20a00000e",
    "wallet" : {
      "currency" : "USD"
    }
  },

  /* 382 */
  {
    "_id" : "553e082a14c5d93715000022",
    "wallet" : {
      "currency" : "EUR"
    }
  },

  /* 383 */
  {
    "_id" : "5544ebb92f9b89e754000012",
    "wallet" : {
      "currency" : "EUR"
    }
  },

  /* 384 */
  {
    "_id" : "55474954170544b33a00001a",
    "wallet" : {
      "currency" : "EUR"
    }
  },

  /* 385 */
  {
    "_id" : "554b2d9d258eefd732000094",
    "wallet" : {
      "currency" : "USD"
    }
  },

  /* 386 */
  {
    "_id" : "554b8cc22793b2323d000021",
    "wallet" : {
      "currency" : "EUR"
    }
  },

  /* 387 */
  {
    "_id" : "554d1eb230e40cdd2100000b",
    "wallet" : {
      "currency" : "USD"
    }
  },

  /* 388 */
  {
    "_id" : "5550b4d3a54ec1506f00000f",
    "wallet" : {
      "currency" : "EUR"
    }
  },

  /* 389 */
  {
    "_id" : "5555c4160d2c61f54e00002d",
    "wallet" : {
      "currency" : "USD"
    }
  },

  /* 390 */
  {
    "_id" : "555ec1f78fda978b01000019",
    "wallet" : {
      "currency" : "USD"
    }
  },

  /* 391 */
  {
    "_id" : "555edb0fee3c4f230500000a",
    "wallet" : {
      "currency" : "EUR"
    }
  },

  /* 392 */
  {
    "_id" : "5564f5bb9249e0a43900004f",
    "wallet" : {
      "currency" : "USD"
    }
  },

  /* 393 */
  {
    "_id" : "556570d5f33bcd780c000018",
    "wallet" : {
      "currency" : "USD"
    }
  },

  /* 394 */
  {
    "_id" : "556728382099e64c1a000018",
    "wallet" : {
      "currency" : "USD"
    }
  },

  /* 395 */
  {
    "_id" : "556848682099e64c1a0000d0",
    "wallet" : {
      "currency" : "USD"
    }
  },

  /* 396 */
  {
    "_id" : "556c40833af50de85e000012",
    "wallet" : {
      "currency" : "USD"
    }
  },

  /* 397 */
  {
    "_id" : "556c892e4a06d6c06f00004c",
    "wallet" : {
      "currency" : "USD"
    }
  },

  /* 398 */
  {
    "_id" : "556db3e94f0e05316e00003a",
    "wallet" : {
      "currency" : "USD"
    }
  },

  /* 399 */
  {
    "_id" : "557875af26bf290a6600004b",
    "wallet" : {
      "currency" : "USD"
    }
  },

  /* 400 */
  {
    "_id" : "55787683de71671039000058",
    "wallet" : {
      "currency" : "USD"
    }
  },

  /* 401 */
  {
    "_id" : "55795970de716710390000a5",
    "wallet" : {
      "currency" : "USD"
    }
  },

  /* 402 */
  {
    "_id" : "557fe5e05253f2275200014d",
    "wallet" : {
      "currency" : "USD"
    }
  },

  /* 403 */
  {
    "_id" : "557ff5bb32d1fe386c0000d8",
    "wallet" : {
      "currency" : "USD"
    }
  },

  /* 404 */
  {
    "_id" : "55809a6a28c0b89f2d00001a",
    "wallet" : {
      "currency" : "USD"
    }
  },

  /* 405 */
  {
    "_id" : "5582d1426cbf86ec3f00000b",
    "wallet" : {
      "currency" : "USD"
    }
  },

  /* 406 */
  {
    "_id" : "55883a2fe9d20e83780000b1",
    "wallet" : {
      "currency" : "USD"
    }
  },

  /* 407 */
  {
    "_id" : "55893ed4c9d47e2844000010",
    "wallet" : {
      "currency" : "USD"
    }
  },

  /* 408 */
  {
    "_id" : "558c17419c1fb8cd1700001e",
    "wallet" : {
      "currency" : "USD"
    }
  },

  /* 409 */
  {
    "_id" : "558c282248f9ab9f3e000034",
    "wallet" : {
      "currency" : "USD"
    }
  },

  /* 410 */
  {
    "_id" : "558d125f48f9ab9f3e000047",
    "wallet" : {
      "currency" : "EUR"
    }
  },

  /* 411 */
  {
    "_id" : "559b8c63943a75046e000031",
    "wallet" : {
      "currency" : "USD"
    }
  },

  /* 412 */
  {
    "_id" : "559bf8f9d8116fde26000038",
    "wallet" : {
      "currency" : "EUR"
    }
  },

  /* 413 */
  {
    "_id" : "559ffcfb6d7f4d591e00000b",
    "wallet" : {
      "currency" : "USD"
    }
  },

  /* 414 */
  {
    "_id" : "55aae922dfbabc3d0c000047",
    "wallet" : {
      "currency" : "USD"
    }
  },

  /* 415 */
  {
    "_id" : "55acc2965653f4a55100000f",
    "wallet" : {
      "currency" : "USD"
    }
  },

  /* 416 */
  {
    "_id" : "55acc2faa6e707ab69000038",
    "wallet" : {
      "currency" : "USD"
    }
  },

  /* 417 */
  {
    "_id" : "55acc3ce372e71c65800000b",
    "wallet" : {
      "currency" : "USD"
    }
  },

  /* 418 */
  {
    "_id" : "55acc432372e71c65800000c",
    "wallet" : {
      "currency" : "USD"
    }
  },

  /* 419 */
  {
    "_id" : "55acc45dbcd598835900000a",
    "wallet" : {
      "currency" : "USD"
    }
  },

  /* 420 */
  {
    "_id" : "55acc518a6e707ab69000039",
    "wallet" : {
      "currency" : "USD"
    }
  },

  /* 421 */
  {
    "_id" : "55af719937a24e4177000047",
    "wallet" : {
      "currency" : "USD"
    }
  },

  /* 422 */
  {
    "_id" : "55b51686dc7e5a601e000017",
    "wallet" : {
      "currency" : "USD"
    }
  },

  /* 423 */
  {
    "_id" : "55b5624fd1a789f832000019",
    "wallet" : {
      "currency" : "USD"
    }
  },

  /* 424 */
  {
    "_id" : "55b6426a07f5d99368000017",
    "wallet" : {
      "currency" : "USD"
    }
  },

  /* 425 */
  {
    "_id" : "55b642c107f5d99368000018",
    "wallet" : {
      "currency" : "USD"
    }
  },

  /* 426 */
  {
    "_id" : "55b6444f676253205d000030",
    "wallet" : {
      "currency" : "USD"
    }
  },

  /* 427 */
  {
    "_id" : "55cb14ed934683182d00006d",
    "wallet" : {
      "currency" : "USD"
    }
  },

  /* 428 */
  {
    "_id" : "55ce42809ca35f604600002f",
    "wallet" : {
      "currency" : "USD"
    }
  },

  /* 429 */
  {
    "_id" : "55e460b0de14905f23000182",
    "wallet" : {
      "currency" : "USD"
    }
  },

  /* 430 */
  {
    "_id" : "55e46b4ede14905f23000192",
    "wallet" : {
      "currency" : "USD"
    }
  },

  /* 431 */
  {
    "_id" : "55e56601de14905f230001c7",
    "wallet" : {
      "currency" : "USD"
    }
  },

  /* 432 */
  {
    "_id" : "55e731921aa825e16d000195",
    "wallet" : {
      "currency" : "USD"
    }
  },

  /* 433 */
  {
    "_id" : "55e731bd1aa825e16d00019d",
    "wallet" : {
      "currency" : "USD"
    }
  },

  /* 434 */
  {
    "_id" : "55e813801edb83d55400012e",
    "wallet" : {
      "currency" : "USD"
    }
  },

  /* 435 */
  {
    "_id" : "55e81a9c1aa825e16d0001ca",
    "wallet" : {
      "currency" : "USD"
    }
  },

  /* 436 */
  {
    "_id" : "55e85c2c4e43fc4e2d000019",
    "wallet" : {
      "currency" : "USD"
    }
  },

  /* 437 */
  {
    "_id" : "55e888864e43fc4e2d000046",
    "wallet" : {
      "currency" : "USD"
    }
  },

  /* 438 */
  {
    "_id" : "55e95223e0cb6e2d4900000a",
    "wallet" : {
      "currency" : "USD"
    }
  },

  /* 439 */
  {
    "_id" : "55e95957f6e75cfb5900000c",
    "wallet" : {
      "currency" : "USD"
    }
  },

  /* 440 */
  {
    "_id" : "55f6e50668c3a0fd6b000057",
    "wallet" : {
      "currency" : "USD"
    }
  },

  /* 441 */
  {
    "_id" : "55f723494af45b165e000027",
    "wallet" : {
      "currency" : "USD"
    }
  },

  /* 442 */
  {
    "_id" : "55f9a0ad1216afc455000014",
    "wallet" : {
      "currency" : "USD"
    }
  },

  /* 443 */
  {
    "_id" : "55f9a25a2d6200bf2c00002c",
    "wallet" : {
      "currency" : "USD"
    }
  },

  /* 444 */
  {
    "_id" : "55f9a5b21216afc45500001d",
    "wallet" : {
      "currency" : "USD"
    }
  },

  /* 445 */
  {
    "_id" : "56041713749b850b20000027",
    "wallet" : {
      "currency" : "USD"
    }
  },

  /* 446 */
  {
    "_id" : "560563372b45f4b3080003d6",
    "wallet" : {
      "currency" : "USD"
    }
  },

  /* 447 */
  {
    "_id" : "5608f12afd5c9e196f00009e",
    "wallet" : {
      "currency" : "USD"
    }
  },

  /* 448 */
  {
    "_id" : "560951e0fd5c9e196f0000ee",
    "wallet" : {
      "currency" : "USD"
    }
  },

  /* 449 */
  {
    "_id" : "560b8990f0cd8c000000000f",
    "wallet" : {
      "currency" : "USD"
    }
  },

  /* 450 */
  {
    "_id" : "560b8a44a7e991000000000f",
    "wallet" : {
      "currency" : "USD"
    }
  },

  /* 451 */
  {
    "_id" : "560b8ae968321e000000000f",
    "wallet" : {
      "currency" : "USD"
    }
  },

  /* 452 */
  {
    "_id" : "560b8b4e4d0e68000000000f",
    "wallet" : {
      "currency" : "USD"
    }
  },

  /* 453 */
  {
    "_id" : "560b8bb38024b0000000000f",
    "wallet" : {
      "currency" : "USD"
    }
  },

  /* 454 */
  {
    "_id" : "560b8c188ad6c3000000000f",
    "wallet" : {
      "currency" : "USD"
    }
  },

  /* 455 */
  {
    "_id" : "560b8c67ca3399000000000f",
    "wallet" : {
      "currency" : "USD"
    }
  },

  /* 456 */
  {
    "_id" : "560b8c80775679000000000f",
    "wallet" : {
      "currency" : "USD"
    }
  },

  /* 457 */
  {
    "_id" : "560b8d25d30573000000000f",
    "wallet" : {
      "currency" : "USD"
    }
  },

  /* 458 */
  {
    "_id" : "560b8d5dbdd37f000000000f",
    "wallet" : {
      "currency" : "USD"
    }
  },

  /* 459 */
  {
    "_id" : "560b8dd52a059b000000000f",
    "wallet" : {
      "currency" : "USD"
    }
  },

  /* 460 */
  {
    "_id" : "560b8e3007ce78000000000f",
    "wallet" : {
      "currency" : "USD"
    }
  },

  /* 461 */
  {
    "_id" : "560b8e7faf1a63000000000f",
    "wallet" : {
      "currency" : "USD"
    }
  },

  /* 462 */
  {
    "_id" : "560b916aee479f000000000f",
    "wallet" : {
      "currency" : "USD"
    }
  },

  /* 463 */
  {
    "_id" : "560b99ce9205029e0000000f",
    "wallet" : {
      "currency" : "USD"
    }
  },

  /* 464 */
  {
    "_id" : "560b9a36064bdd270100000f",
    "wallet" : {
      "currency" : "USD"
    }
  },

  /* 465 */
  {
    "_id" : "560b9d5dfcb9b80d0500000d",
    "wallet" : {
      "currency" : "USD"
    }
  },

  /* 466 */
  {
    "_id" : "560b9e35643756fb0500000d",
    "wallet" : {
      "currency" : "USD"
    }
  },

  /* 467 */
  {
    "_id" : "560ba3e3bb5eaf990b00000d",
    "wallet" : {
      "currency" : "USD"
    }
  },

  /* 468 */
  {
    "_id" : "560ba4830ef237680c00000d",
    "wallet" : {
      "currency" : "USD"
    }
  },

  /* 469 */
  {
    "_id" : "560bae3283ef53d64b00004b",
    "wallet" : {
      "currency" : "USD"
    }
  },

  /* 470 */
  {
    "_id" : "560bd8a1590289744800000d",
    "wallet" : {
      "currency" : "USD"
    }
  },

  /* 471 */
  {
    "_id" : "560bf2eb766fd12c6700000b",
    "wallet" : {
      "currency" : "USD"
    }
  },

  /* 472 */
  {
    "_id" : "560e54afcf9a07250e00004c",
    "wallet" : {
      "currency" : "USD"
    }
  },

  /* 473 */
  {
    "_id" : "560f31ba0472c93f4b000052",
    "wallet" : {
      "currency" : "USD"
    }
  },

  /* 474 */
  {
    "_id" : "56155f89a1b06b8e08000181",
    "wallet" : {
      "currency" : "USD"
    }
  },

  /* 475 */
  {
    "_id" : "5617c4ca7ec22c2458000232",
    "wallet" : {
      "currency" : "USD"
    }
  },

  /* 476 */
  {
    "_id" : "5624c368f22ca19334000050",
    "wallet" : {
      "currency" : "USD"
    }
  },

  /* 477 */
  {
    "_id" : "56268268f22ca19334000fa2",
    "wallet" : {
      "currency" : "USD"
    }
  },

  /* 478 */
  {
    "_id" : "56279c08f22ca19334000fe3",
    "wallet" : {
      "currency" : "USD"
    }
  },

  /* 479 */
  {
    "_id" : "56279cbd7ea5f4d41b0001b5",
    "wallet" : {
      "currency" : "USD"
    }
  },

  /* 480 */
  {
    "_id" : "56309ec5d920344f2600001a",
    "wallet" : {
      "currency" : "USD"
    }
  },

  /* 481 */
  {
    "_id" : "5632a8ef9b8f6dd33600000c",
    "wallet" : {
      "currency" : "USD"
    }
  },

  /* 482 */
  {
    "_id" : "563447753baf52d4130000ce",
    "wallet" : {
      "currency" : "USD"
    }
  },

  /* 483 */
  {
    "_id" : "56379caf3858c8a95300003c",
    "wallet" : {
      "currency" : "EUR"
    }
  },

  /* 484 */
  {
    "_id" : "5639318c6e9824d605000044",
    "wallet" : {
      "currency" : "USD"
    }
  },

  /* 485 */
  {
    "_id" : "5639a62c6e9824d605000051",
    "wallet" : {
      "currency" : "USD"
    }
  },

  /* 486 */
  {
    "_id" : "563b17236e9824d605000a94",
    "wallet" : {
      "currency" : "USD"
    }
  },

  /* 487 */
  {
    "_id" : "564252d24d7d5f243400060a",
    "wallet" : {
      "currency" : "USD"
    }
  },

  /* 488 */
  {
    "_id" : "56430ea24d7d5f243400079d",
    "wallet" : {
      "currency" : "USD"
    }
  },

  /* 489 */
  {
    "_id" : "564368061d7fb5a714000112",
    "wallet" : {
      "currency" : "USD"
    }
  },

  /* 490 */
  {
    "_id" : "56444d491d7fb5a71400021f",
    "wallet" : {
      "currency" : "USD"
    }
  },

  /* 491 */
  {
    "_id" : "5645b91b1339dfd716000023",
    "wallet" : {
      "currency" : "USD"
    }
  },

  /* 492 */
  {
    "_id" : "5645d51161e992092f00008b",
    "wallet" : {
      "currency" : "USD"
    }
  },

  /* 493 */
  {
    "_id" : "56460120f7e6414058000016",
    "wallet" : {
      "currency" : "USD"
    }
  },

  /* 494 */
  {
    "_id" : "56488570f7e64140580004f8",
    "wallet" : {
      "currency" : "USD"
    }
  },

  /* 495 */
  {
    "_id" : "5649c71fcd9eeecd1400000e",
    "wallet" : {
      "currency" : "USD"
    }
  },

  /* 496 */
  {
    "_id" : "564a2c2b185ae6db64000023",
    "wallet" : {
      "currency" : "USD"
    }
  },

  /* 497 */
  {
    "_id" : "564b5cec0adc28000000000d",
    "wallet" : {
      "currency" : "USD"
    }
  },

  /* 498 */
  {
    "_id" : "564b5dd2ecf688000000000d",
    "wallet" : {
      "currency" : "USD"
    }
  },

  /* 499 */
  {
    "_id" : "564eb5c6cd9cf6d43d00053f",
    "wallet" : {
      "currency" : "USD"
    }
  },

  /* 500 */
  {
    "_id" : "56536aef2f0771ec410000d0",
    "wallet" : {
      "currency" : "USD"
    }
  },

  /* 501 */
  {
    "_id" : "5656e3191ef6ea6a4b00001c",
    "wallet" : {
      "currency" : "USD"
    }
  },

  /* 502 */
  {
    "_id" : "56604f769c696f0322000049",
    "wallet" : {
      "currency" : "USD"
    }
  },

  /* 503 */
  {
    "_id" : "56616cbe4fcad8460f0001a5",
    "wallet" : {
      "currency" : "USD"
    }
  },

  /* 504 */
  {
    "_id" : "566178c14fcad8460f000262",
    "wallet" : {
      "currency" : "USD"
    }
  },

  /* 505 */
  {
    "_id" : "56688a6c05b2828e5000003a",
    "wallet" : {
      "currency" : "USD"
    }
  },

  /* 506 */
  {
    "_id" : "566eee5d39e5b85a0f000044",
    "wallet" : {
      "currency" : "USD"
    }
  },

  /* 507 */
  {
    "_id" : "56710b1ca34d1bf16000046e",
    "wallet" : {
      "currency" : "USD"
    }
  },

  /* 508 */
  {
    "_id" : "567abc5a1e752c8669000076",
    "wallet" : {
      "currency" : "USD"
    }
  },

  /* 509 */
  {
    "_id" : "567fe9b3c99148892c000133",
    "wallet" : {
      "currency" : "USD"
    }
  },

  /* 510 */
  {
    "_id" : "5683bdf7827b89911b00006a",
    "wallet" : {
      "currency" : "USD"
    }
  },

  /* 511 */
  {
    "_id" : "56990496686e5eed7d000022",
    "wallet" : {
      "currency" : "USD"
    }
  },

  /* 512 */
  {
    "_id" : "569cfd613bfb2cad76000065",
    "wallet" : {
      "currency" : "USD"
    }
  },

  /* 513 */
  {
    "_id" : "569d5457b7e01aec40000023",
    "wallet" : {
      "currency" : "USD"
    }
  },

  /* 514 */
  {
    "_id" : "569e9098d8ef0a6b69000050",
    "wallet" : {
      "currency" : "USD"
    }
  },

  /* 515 */
  {
    "_id" : "56a0fa8ef0ac1a9105000074",
    "wallet" : {
      "currency" : "USD"
    }
  },

  /* 516 */
  {
    "_id" : "56b0f2cf38a99d7f150000f6",
    "wallet" : {
      "currency" : "EUR"
    }
  },

  /* 517 */
  {
    "_id" : "56b1ce7736535bc77f000282",
    "wallet" : {
      "currency" : "USD"
    }
  },

  /* 518 */
  {
    "_id" : "56bb00aefb5839f31600001d",
    "wallet" : {
      "currency" : "USD"
    }
  },

  /* 519 */
  {
    "_id" : "56bc32b310d688b44300001c",
    "wallet" : {
      "currency" : "USD"
    }
  },

  /* 520 */
  {
    "_id" : "56bdb7566d799cfd1f000025",
    "wallet" : {
      "currency" : "USD"
    }
  },

  /* 521 */
  {
    "_id" : "56bdb7a96d799cfd1f00002c",
    "wallet" : {
      "currency" : "EUR"
    }
  },

  /* 522 */
  {
    "_id" : "56c4642a96e926e62c00002a",
    "wallet" : {
      "currency" : "EUR"
    }
  },

  /* 523 */
  {
    "_id" : "56c49224eeb3e2387b000024",
    "wallet" : {
      "currency" : "USD"
    }
  },

  /* 524 */
  {
    "_id" : "56ca31276427673c1d000108",
    "wallet" : {
      "currency" : "USD"
    }
  },

  /* 525 */
  {
    "_id" : "56cae1b2cf88963122000074",
    "wallet" : {
      "currency" : "USD"
    }
  },

  /* 526 */
  {
    "_id" : "56d4ad1799cac8583f0076d7",
    "wallet" : {
      "currency" : "USD"
    }
  },

  /* 527 */
  {
    "_id" : "56dfdbad43a2b92e040011c1",
    "wallet" : {
      "currency" : "USD"
    }
  },

  /* 528 */
  {
    "_id" : "56e15b1483354e5c71000164",
    "wallet" : {
      "currency" : "EUR"
    }
  },

  /* 529 */
  {
    "_id" : "56e167c183354e5c7100041f",
    "wallet" : {
      "currency" : "USD"
    }
  },

  /* 530 */
  {
    "_id" : "56e87005087b2bb25300301a",
    "wallet" : {
      "currency" : "USD"
    }
  },

  /* 531 */
  {
    "_id" : "56e94b7a87a317393400046c",
    "wallet" : {
      "currency" : "USD"
    }
  },

  /* 532 */
  {
    "_id" : "56f130dd8a140b3b56001926",
    "wallet" : {
      "currency" : "USD"
    }
  },

  /* 533 */
  {
    "_id" : "56f157fc8a140b3b56001d34",
    "wallet" : {
      "currency" : "USD"
    }
  },

  /* 534 */
  {
    "_id" : "56f45072cfe9ee0e11001af3",
    "wallet" : {
      "currency" : "USD"
    }
  },

  /* 535 */
  {
    "_id" : "56f8d5d8cfe9ee0e11005b06",
    "wallet" : {
      "currency" : "USD"
    }
  },

  /* 536 */
  {
    "_id" : "56f8d725cfe9ee0e11005b17",
    "wallet" : {
      "currency" : "USD"
    }
  },

  /* 537 */
  {
    "_id" : "56f8dd07ec02ca310800559f",
    "wallet" : {
      "currency" : "USD"
    }
  },

  /* 538 */
  {
    "_id" : "56fa8a87cfe9ee0e110083aa",
    "wallet" : {
      "currency" : "USD"
    }
  },

  /* 539 */
  {
    "_id" : "56fbbe7eec02ca310800a4d6",
    "wallet" : {
      "currency" : "USD"
    }
  },

  /* 540 */
  {
    "_id" : "56fcdea8a00d9b847700263d",
    "wallet" : {
      "currency" : "USD"
    }
  },

  /* 541 */
  {
    "_id" : "56fd2ec0b587607f7e000c9c",
    "wallet" : {
      "currency" : "USD"
    }
  },

  /* 542 */
  {
    "_id" : "570205e237e092197100035d",
    "wallet" : {
      "currency" : "USD"
    }
  },

  /* 543 */
  {
    "_id" : "57031e0d37e092197100274a",
    "wallet" : {
      "currency" : "USD"
    }
  },

  /* 544 */
  {
    "_id" : "57038da2d29df0ab240001a8",
    "wallet" : {
      "currency" : "USD"
    }
  },

  /* 545 */
  {
    "_id" : "57038e5bd29df0ab24000201",
    "wallet" : {
      "currency" : "USD"
    }
  },

  /* 546 */
  {
    "_id" : "57064990c265550a2e000448",
    "wallet" : {
      "currency" : "USD"
    }
  },

  /* 547 */
  {
    "_id" : "570649d680957c620d00048c",
    "wallet" : {
      "currency" : "USD"
    }
  },

  /* 548 */
  {
    "_id" : "57064a3dc265550a2e000483",
    "wallet" : {
      "currency" : "USD"
    }
  },

  /* 549 */
  {
    "_id" : "570bb225a95b45473f0011a8",
    "wallet" : {
      "currency" : "USD"
    }
  },

  /* 550 */
  {
    "_id" : "570db85085bda98d6c00218f",
    "wallet" : {
      "currency" : "USD"
    }
  },

  /* 551 */
  {
    "_id" : "5714ceeaa082450c2100575d",
    "wallet" : {
      "currency" : "USD"
    }
  },

  /* 552 */
  {
    "_id" : "571f1bcc1fda77924c0011b7",
    "wallet" : {
      "currency" : "EUR"
    }
  },

  /* 553 */
  {
    "_id" : "571f550f1fda77924c002229",
    "wallet" : {
      "currency" : "USD"
    }
  },

  /* 554 */
  {
    "_id" : "571f8ee11fda77924c003876",
    "wallet" : {
      "currency" : "USD"
    }
  },

  /* 555 */
  {
    "_id" : "572c7b526e11712c5e000696",
    "wallet" : {
      "currency" : "USD"
    }
  },

  /* 556 */
  {
    "_id" : "57305095e34a1fdb0a004df9",
    "wallet" : {
      "currency" : "USD"
    }
  },

  /* 557 */
  {
    "_id" : "5736412faf0b13da060005cc",
    "wallet" : {
      "currency" : "USD"
    }
  },

  /* 558 */
  {
    "_id" : "574258a9e84c21f953004f17",
    "wallet" : {
      "currency" : "USD"
    }
  },

  /* 559 */
  {
    "_id" : "5743996ee7c874e422001f6c",
    "wallet" : {
      "currency" : "USD"
    }
  },

  /* 560 */
  {
    "_id" : "57445f8f9699b74f2c00078d",
    "wallet" : {
      "currency" : "USD"
    }
  },

  /* 561 */
  {
    "_id" : "5746b9017309d2b80e0000bc",
    "wallet" : {
      "currency" : "USD"
    }
  },

  /* 562 */
  {
    "_id" : "574839e9a86bfe5373002a76",
    "wallet" : {
      "currency" : "USD"
    }
  },

  /* 563 */
  {
    "_id" : "574c224bf4712c7d3a000468",
    "wallet" : {
      "currency" : "USD"
    }
  },

  /* 564 */
  {
    "_id" : "574da157125f8eb927001cd4",
    "wallet" : {
      "currency" : "USD"
    }
  },

  /* 565 */
  {
    "_id" : "9444c9fd2d62af15290006e7",
    "wallet" : {
      "currency" : "USD"
    }
  }
]